README
setup.py
ansilbe/__init__.py
ansilbe.egg-info/PKG-INFO
ansilbe.egg-info/SOURCES.txt
ansilbe.egg-info/dependency_links.txt
ansilbe.egg-info/requires.txt
ansilbe.egg-info/top_level.txt